splunktaucclib/__init__.py
splunktaucclib/alert_actions_base.py
splunktaucclib/cim_actions.py
splunktaucclib/common/__init__.py
splunktaucclib/common/log.py
splunktaucclib/common/xml_dom_parser.py
splunktaucclib/config.py
splunktaucclib/global_config/__init__.py
splunktaucclib/global_config/configuration.py
splunktaucclib/global_config/schema.py
splunktaucclib/legacy/__init__.py
splunktaucclib/legacy/credentials.py
splunktaucclib/legacy/rest.py
splunktaucclib/legacy/util.py
splunktaucclib/modinput_wrapper/__init__.py
splunktaucclib/modinput_wrapper/base_modinput.py
splunktaucclib/rest_handler/__init__.py
splunktaucclib/rest_handler/admin_external.py
splunktaucclib/rest_handler/base.py
splunktaucclib/rest_handler/base_hook_mixin.py
splunktaucclib/rest_handler/cred_mgmt.py
splunktaucclib/rest_handler/credentials.py
splunktaucclib/rest_handler/datainput.py
splunktaucclib/rest_handler/eai.py
splunktaucclib/rest_handler/endpoint/__init__.py
splunktaucclib/rest_handler/endpoint/converter.py
splunktaucclib/rest_handler/endpoint/field.py
splunktaucclib/rest_handler/endpoint/validator.py
splunktaucclib/rest_handler/entity.py
splunktaucclib/rest_handler/error.py
splunktaucclib/rest_handler/error_ctl.py
splunktaucclib/rest_handler/handler.py
splunktaucclib/rest_handler/multimodel.py
splunktaucclib/rest_handler/normaliser.py
splunktaucclib/rest_handler/poster.py
splunktaucclib/rest_handler/schema.py
splunktaucclib/rest_handler/teardown.py
splunktaucclib/rest_handler/util.py
splunktaucclib/rest_handler/validator.py
splunktaucclib/splunk_aoblib/__init__.py
splunktaucclib/splunk_aoblib/rest_helper.py
splunktaucclib/splunk_aoblib/rest_migration.py
splunktaucclib/splunk_aoblib/setup_util.py
splunktaucclib/splunk_aoblib/utility.py
splunktaucclib-7.0.0.dist-info/LICENSE
splunktaucclib-7.0.0.dist-info/METADATA
splunktaucclib-7.0.0.dist-info/WHEEL
splunktaucclib-7.0.0.dist-info/RECORD
