Metadata-Version: 2.1
Name: splunktaucclib
Version: 7.0.0
Summary: 
License: Apache-2.0
Author: Splunk
Author-email: addonfactory@splunk.com
Requires-Python: >=3.7,<3.14
Classifier: License :: OSI Approved :: Apache Software License
Classifier: Programming Language :: Python :: 3
Classifier: Programming Language :: Python :: 3.7
Classifier: Programming Language :: Python :: 3.8
Classifier: Programming Language :: Python :: 3.9
Classifier: Programming Language :: Python :: 3.10
Classifier: Programming Language :: Python :: 3.11
Requires-Dist: PySocks (>=1.7.1,<2.0.0)
Requires-Dist: defusedxml (>=0.7)
Requires-Dist: solnlib (>=5)
Requires-Dist: splunk-sdk (>=2.0.2)
Requires-Dist: urllib3 (<2)
